{"BTC": "SHORT", "ETH": "LONG", "USDC": "LONG", "SOL": "LONG", "HYPE": "SHORT", "DOGE": "SHORT", "XRP": "SHORT", "WLD": "SHORT", "USDG": "SHORT", "ZEC": "SHORT", "RE": "LONG", "SUI": "LONG", "TRX": "SHORT", "GRAM": "SHORT", "OKB": "SHORT", "BNB": "LONG", "IP": "LONG", "XAUT": "SHORT", "FIL": "LONG", "RESOLV": "SHORT", "TRUMP": "LONG", "UNI": "LONG", "ADA": "SHORT", "BASED": "LONG", "NEAR": "LONG", "LTC": "SHORT", "XLM": "LONG", "PEPE": "SHORT", "BICO": "LONG", "LINK": "LONG", "LAYER": "LONG", "PI": "SHORT", "PAXG": "SHORT", "BCH": "LONG", "XPL": "LONG", "ONDO": "LONG", "ALLO": "LONG", "AVAX": "LONG", "CC": "LONG", "LIT": "SHORT", "JTO": "LONG", "PUMP": "LONG", "DOT": "LONG", "ENA": "LONG", "MMT": "SHORT", "EIGEN": "LONG", "ASTER": "LONG", "WLFI": "LONG", "DYDX": "LONG", "PENGU": "SHORT", "ICP": "LONG", "SD": "SHORT", "AAVE": "LONG", "ZAMA": "SHORT", "G": "SHORT", "MEGA": "LONG", "CHZ": "LONG", "ORDI": "LONG", "AXS": "LONG", "STRK": "SHORT", "BONK": "LONG", "INJ": "LONG", "HMSTR": "LONG", "GRASS": "LONG", "TIA": "LONG", "SHIB": "LONG", "JUP": "SHORT", "KAT": "SHORT", "SPACE": "LONG", "ETC": "LONG", "OP": "SHORT", "ID": "LONG", "CORE": "SHORT", "BREV": "SHORT", "W": "SHORT", "APE": "LONG", "ETHFI": "LONG", "APT": "LONG", "TNSR": "SHORT", "ZRO": "SHORT", "S": "SHORT", "MON": "LONG", "AR": "LONG", "MET": "LONG", "ARB": "LONG", "FET": "LONG", "DASH": "LONG", "PYTH": "LONG", "LRC": "SHORT", "IRYS": "LONG", "AI": "LONG", "ALGO": "LONG", "RENDER": "LONG", "LDO": "LONG", "MORPHO": "SHORT", "SEI": "SHORT", "POL": "LONG", "OFC": "LONG", "HBAR": "LONG", "CFX": "LONG"}