{"BTC": "LONG", "ETH": "LONG", "USDC": "LONG", "SOL": "LONG", "HYPE": "LONG", "XRP": "LONG", "DOGE": "LONG", "DYDX": "SHORT", "BASED": "LONG", "XLM": "LONG", "XAUT": "LONG", "MON": "LONG", "LIT": "LONG", "WLD": "SHORT", "OKB": "LONG", "SUI": "LONG", "RE": "SHORT", "ZEC": "LONG", "AI": "LONG", "ADA": "LONG", "TRX": "LONG", "GRAM": "SHORT", "NES": "LONG", "PEPE": "LONG", "BNB": "LONG", "USDG": "SHORT", "FIL": "LONG", "BCH": "LONG", "NEAR": "LONG", "PUMP": "LONG", "JTO": "LONG", "LTC": "LONG", "ORDI": "SHORT", "TRUMP": "SHORT", "UNI": "LONG", "TAO": "LONG", "ALLO": "LONG", "AAVE": "LONG", "XPL": "SHORT", "PI": "LONG", "LINK": "LONG", "ENA": "LONG", "MET": "LONG", "MORPHO": "SHORT", "PYTH": "LONG", "IP": "LONG", "JUP": "LONG", "ONDO": "LONG", "ICP": "LONG", "CARDS": "SHORT", "AVAX": "LONG", "ACT": "LONG", "PENGU": "SHORT", "CELO": "LONG", "SHIB": "LONG", "GRASS": "LONG", "PAXG": "SHORT", "IOTA": "SHORT", "ETHFI": "SHORT", "STRK": "LONG", "WIF": "LONG", "RESOLV": "LONG", "ZRO": "LONG", "WLFI": "LONG", "CORE": "LONG", "OFC": "SHORT", "FLUID": "SHORT", "NIGHT": "SHORT", "ARB": "LONG", "BIO": "LONG", "APT": "SHORT", "DOT": "SHORT", "OKSOL": "LONG", "BONK": "LONG", "CHZ": "SHORT", "VIRTUAL": "SHORT", "CC": "SHORT", "EDGE": "SHORT", "WET": "SHORT", "HBAR": "LONG", "FET": "SHORT", "OP": "SHORT", "ETC": "LONG", "TIA": "SHORT", "ZAMA": "LONG", "LSK": "LONG", "AR": "SHORT", "CSPR": "LONG", "APE": "SHORT", "KAITO": "LONG", "RENDER": "SHORT", "STETH": "LONG", "AGLD": "SHORT", "MEGA": "SHORT", "INJ": "SHORT", "CRV": "LONG", "BICO": "LONG", "PROS": "LONG", "ASTER": "SHORT", "MOODENG": "LONG"}